ngwpy/__init__.py
ngwpy/ngw/__init__.py
ngwpy/ngw/constants.py
ngwpy/ngw/context/__init__.py
ngwpy/ngw/data/__init__.py
ngwpy/ngw/report/__init__.py
ngwpy/ngw/strategy/__init__.py
ngwpy/ngw/utils/__init__.py
ngwpy-0.0.1.dist-info/METADATA
ngwpy-0.0.1.dist-info/WHEEL
ngwpy-0.0.1.dist-info/top_level.txt
ngwpy-0.0.1.dist-info/RECORD
