Metadata-Version: 2.1
Name: ngwpy
Version: 0.0.1
Summary: stock backtest framework
Home-page: https://github.com/296348304/ngwpy
Author: Wang Jian
Author-email: 296348304@qq.com
License: UNKNOWN
Platform: UNKNOWN
Classifier: Programming Language :: Python :: 3
Classifier: License :: OSI Approved :: MIT License
Classifier: Operating System :: OS Independent
Requires-Python: >=3.7
